snowdrop_tangled_alphazero/__init__.py
snowdrop_tangled_alphazero/game/__init__.py
snowdrop_tangled_alphazero/game/Game.py
snowdrop_tangled_alphazero/game/TangledGame.py
snowdrop_tangled_alphazero/main.py
snowdrop_tangled_alphazero/monte_carlo/__init__.py
snowdrop_tangled_alphazero/monte_carlo/AZMCTS.py
snowdrop_tangled_alphazero/neural_net/__init__.py
snowdrop_tangled_alphazero/neural_net/AlphaZeroNet.py
snowdrop_tangled_alphazero/neural_net/NeuralNet.py
snowdrop_tangled_alphazero/results/graph_11_fixed_token/lookup_table/quantum_annealing/0.5_350_10000/best.pth
snowdrop_tangled_alphazero/results/graph_11_fixed_token/lookup_table/quantum_annealing/best.pth
snowdrop_tangled_alphazero/results/graph_11_fixed_token/lookup_table/quantum_annealing/challenger.pth
snowdrop_tangled_alphazero/results/graph_11_fixed_token/lookup_table/quantum_annealing/checkpoint_0.pth.examples
snowdrop_tangled_alphazero/results/graph_11_fixed_token/lookup_table/quantum_annealing/checkpoint_1.pth
snowdrop_tangled_alphazero/results/graph_11_fixed_token/lookup_table/quantum_annealing/checkpoint_1.pth.examples
snowdrop_tangled_alphazero/results/graph_11_fixed_token/lookup_table/quantum_annealing/checkpoint_2.pth.examples
snowdrop_tangled_alphazero/results/graph_11_fixed_token/lookup_table/quantum_annealing/elo_list.pkl
snowdrop_tangled_alphazero/results/graph_11_fixed_token/lookup_table/quantum_annealing/temp.pth
snowdrop_tangled_alphazero/results/graph_19_fixed_token/lookup_table/quantum_annealing/best.pth
snowdrop_tangled_alphazero/results/graph_19_fixed_token/lookup_table/quantum_annealing/challenger.pth
snowdrop_tangled_alphazero/results/graph_19_fixed_token/lookup_table/quantum_annealing/checkpoint_0.pth.examples
snowdrop_tangled_alphazero/results/graph_19_fixed_token/lookup_table/quantum_annealing/checkpoint_1.pth
snowdrop_tangled_alphazero/results/graph_19_fixed_token/lookup_table/quantum_annealing/checkpoint_1.pth.examples
snowdrop_tangled_alphazero-0.0.5.dist-info/LICENSE
snowdrop_tangled_alphazero-0.0.5.dist-info/METADATA
snowdrop_tangled_alphazero-0.0.5.dist-info/WHEEL
snowdrop_tangled_alphazero-0.0.5.dist-info/RECORD
