Metadata-Version: 2.3
Name: snowdrop-tangled-alphazero
Version: 0.0.5
Summary: Train AlphaZero agents for the Tangled game
License: MIT
Author: Geordie Rose
Author-email: greatblueheron@users.noreply.github.com
Requires-Python: >=3.11,<3.14
Classifier: License :: OSI Approved :: MIT License
Classifier: Programming Language :: Python :: 3
Classifier: Programming Language :: Python :: 3.11
Classifier: Programming Language :: Python :: 3.12
Classifier: Programming Language :: Python :: 3.13
Requires-Dist: coloredlogs (>=15.0.1)
Requires-Dist: snowdrop-adjudicators (>=0.0.8)
Requires-Dist: snowdrop-special-adjudicators (>=0.0.3)
Requires-Dist: snowdrop-tangled-game-engine (>=1.0.7)
Requires-Dist: torch (>=2.8.0,<3.0.0)
Project-URL: Bug Tracker, https://github.com/snowdropquantum/snowdrop-tangled-alphazero/issues
Project-URL: Documentation, https://github.com/snowdropquantum/snowdrop-tangled-alphazero
Project-URL: Homepage, https://github.com/snowdropquantum/snowdrop-tangled-alphazero
Project-URL: Repository, https://github.com/snowdropquantum/snowdrop-tangled-alphazero
